gm2kenc.py
PyGM2kEncrypter-1.0.0.dist-info/LICENSE
PyGM2kEncrypter-1.0.0.dist-info/METADATA
PyGM2kEncrypter-1.0.0.dist-info/WHEEL
PyGM2kEncrypter-1.0.0.dist-info/top_level.txt
PyGM2kEncrypter-1.0.0.dist-info/zip-safe
PyGM2kEncrypter-1.0.0.dist-info/RECORD
